atlas_chess-0.0.10.dist-info/METADATA
atlas_chess-0.0.10.dist-info/WHEEL
atlas_chess/__init__.py
atlas_chess/atlas_chess.pypy39-pp73-aarch64-linux-gnu.so
atlas_chess-0.0.10.dist-info/RECORD
