Metadata-Version: 2.4
Name: atlas-chess
Version: 0.0.10
